{
	"textures": [
		{
			"image": "sprites.png",
			"format": "RGBA8888",
			"size": {
				"w": 402,
				"h": 982
			},
			"scale": 1,
			"frames": [
				{
					"filename": "splash/base",
					"rotated": false,
					"trimmed": false,
					"sourceSize": {
						"w": 400,
						"h": 480
					},
					"spriteSourceSize": {
						"x": 0,
						"y": 0,
						"w": 400,
						"h": 480
					},
					"frame": {
						"x": 1,
						"y": 1,
						"w": 400,
						"h": 480
					}
				},
				{
					"filename": "splash/hover",
					"rotated": false,
					"trimmed": false,
					"sourceSize": {
						"w": 400,
						"h": 480
					},
					"spriteSourceSize": {
						"x": 0,
						"y": 0,
						"w": 400,
						"h": 480
					},
					"frame": {
						"x": 1,
						"y": 483,
						"w": 400,
						"h": 480
					}
				},
				{
					"filename": "body",
					"rotated": false,
					"trimmed": false,
					"sourceSize": {
						"w": 16,
						"h": 16
					},
					"spriteSourceSize": {
						"x": 0,
						"y": 0,
						"w": 16,
						"h": 16
					},
					"frame": {
						"x": 1,
						"y": 965,
						"w": 16,
						"h": 16
					}
				},
				{
					"filename": "food",
					"rotated": false,
					"trimmed": false,
					"sourceSize": {
						"w": 16,
						"h": 16
					},
					"spriteSourceSize": {
						"x": 0,
						"y": 0,
						"w": 16,
						"h": 16
					},
					"frame": {
						"x": 19,
						"y": 965,
						"w": 16,
						"h": 16
					}
				},
				{
					"filename": "head/dead",
					"rotated": false,
					"trimmed": false,
					"sourceSize": {
						"w": 16,
						"h": 16
					},
					"spriteSourceSize": {
						"x": 0,
						"y": 0,
						"w": 16,
						"h": 16
					},
					"frame": {
						"x": 37,
						"y": 965,
						"w": 16,
						"h": 16
					}
				},
				{
					"filename": "head/down",
					"rotated": false,
					"trimmed": false,
					"sourceSize": {
						"w": 16,
						"h": 16
					},
					"spriteSourceSize": {
						"x": 0,
						"y": 0,
						"w": 16,
						"h": 16
					},
					"frame": {
						"x": 55,
						"y": 965,
						"w": 16,
						"h": 16
					}
				},
				{
					"filename": "head/left",
					"rotated": false,
					"trimmed": false,
					"sourceSize": {
						"w": 16,
						"h": 16
					},
					"spriteSourceSize": {
						"x": 0,
						"y": 0,
						"w": 16,
						"h": 16
					},
					"frame": {
						"x": 73,
						"y": 965,
						"w": 16,
						"h": 16
					}
				},
				{
					"filename": "head/right",
					"rotated": false,
					"trimmed": false,
					"sourceSize": {
						"w": 16,
						"h": 16
					},
					"spriteSourceSize": {
						"x": 0,
						"y": 0,
						"w": 16,
						"h": 16
					},
					"frame": {
						"x": 91,
						"y": 965,
						"w": 16,
						"h": 16
					}
				},
				{
					"filename": "head/up",
					"rotated": false,
					"trimmed": false,
					"sourceSize": {
						"w": 16,
						"h": 16
					},
					"spriteSourceSize": {
						"x": 0,
						"y": 0,
						"w": 16,
						"h": 16
					},
					"frame": {
						"x": 109,
						"y": 965,
						"w": 16,
						"h": 16
					}
				}
			]
		}
	],
	"meta": {
		"app": "https://www.codeandweb.com/texturepacker",
		"version": "3.0",
		"smartupdate": "$TexturePacker:SmartUpdate:0655874533ae8a95d13cad38941ef517:b170e151aeebcedbb394283419e53cb5:1eabdf11f75e3a4fe3147baf7b5be24b$"
	}
}
